CHANGES.rst
DESCRIPTION.rst
LICENSE
MANIFEST.in
README.md
setup.py
src/ldc_docx/__init__.py
src/ldc_docx/class_lister.py
src/ldc_docx.egg-info/PKG-INFO
src/ldc_docx.egg-info/SOURCES.txt
src/ldc_docx.egg-info/dependency_links.txt
src/ldc_docx.egg-info/entry_points.txt
src/ldc_docx.egg-info/requires.txt
src/ldc_docx.egg-info/top_level.txt
src/ldc_docx/pretrain/__init__.py
src/ldc_docx/pretrain/_docx.py